DjangoLibrary/__init__.py
DjangoLibrary/middleware.py
DjangoLibrary/tests/__init__.py
DjangoLibrary/tests/factories.py
robotframework_djangolibrary-3.0.0.dist-info/LICENSE.txt
robotframework_djangolibrary-3.0.0.dist-info/METADATA
robotframework_djangolibrary-3.0.0.dist-info/WHEEL
robotframework_djangolibrary-3.0.0.dist-info/entry_points.txt
robotframework_djangolibrary-3.0.0.dist-info/top_level.txt
robotframework_djangolibrary-3.0.0.dist-info/RECORD
