Metadata-Version: 2.1
Name: robotframework-djangolibrary
Version: 3.0.0
Summary: A Robot Framework library for Django.
Home-page: https://kitconcept.com
Author: kitconcept GmbH | Timo Stollenwerk
Author-email: stollenwerk@kitconcept.com
License: Apache License 2.0
Keywords: robotframework django test
Platform: UNKNOWN
Classifier: Development Status :: 5 - Production/Stable
Classifier: License :: OSI Approved :: Apache Software License
Classifier: Environment :: Web Environment
Classifier: Framework :: Robot Framework
Classifier: Framework :: Django
Classifier: Framework :: Django :: 1.5
Classifier: Framework :: Django :: 1.6
Classifier: Framework :: Django :: 1.7
Classifier: Framework :: Django :: 1.8
Classifier: Framework :: Django :: 1.9
Classifier: Framework :: Django :: 1.10
Classifier: Framework :: Django :: 1.11
Classifier: Programming Language :: Python :: 2.7
Classifier: Programming Language :: Python :: 3.5
Classifier: Programming Language :: Python :: 3.6
Classifier: Programming Language :: Python :: Implementation :: CPython
Requires-Dist: Django
Requires-Dist: factory-boy
Requires-Dist: requests
Requires-Dist: robotframework
Requires-Dist: robotframework-seleniumlibrary
Requires-Dist: robotframework-debuglibrary
Requires-Dist: six
